pymail/__init__.py
pymail/config.py
pymail/decorators.py
pymail/email_sender.py
pymail/i18n.py
pymail/stats.py
pymail/tools.py
pymail/i18n/messages.yaml
pymail_notify-0.1.6.dist-info/licenses/LICENSE
pymail_notify-0.1.6.dist-info/METADATA
pymail_notify-0.1.6.dist-info/WHEEL
pymail_notify-0.1.6.dist-info/top_level.txt
pymail_notify-0.1.6.dist-info/RECORD
